{"cameraMode":{"drawMode":0,"name":"Shaded","section":"Shading Mode"},"sceneLighting":true,"audioPlay":false,"sceneViewState":{"showFog":true,"showMaterialUpdate":false,"showSkybox":true,"showFlares":true,"showImageEffects":true,"showParticleSystems":true},"in2DMode":false,"pivot":{"x":-2.403188705444336,"y":-0.2707700729370117,"z":2.9313392639160158},"rotation":{"x":-0.10217644274234772,"y":0.8734172582626343,"z":-0.20847931504249574,"w":-0.4280647039413452},"size":16.82186508178711,"orthographic":false}